Xmlstats_py-1.0.1.dist-info/DESCRIPTION.rst
Xmlstats_py-1.0.1.dist-info/METADATA
Xmlstats_py-1.0.1.dist-info/RECORD
Xmlstats_py-1.0.1.dist-info/WHEEL
Xmlstats_py-1.0.1.dist-info/metadata.json
Xmlstats_py-1.0.1.dist-info/top_level.txt
xmlstats/__init__.py
xmlstats/xmlstats.py
