Metadata-Version: 2.0
Name: Xmlstats-py
Version: 1.0.1
Summary: Python client for xmlstats API
Home-page: https://github.com/dwelch2101/Xmlstats-py
Author: Daniel Welch
Author-email: dwelch2012@gmail.com
License: MIT
Platform: UNKNOWN
Requires-Dist: requests
